liionpack/__init__.py
liionpack/_version.py
liionpack/definitions.py
liionpack/logger.py
liionpack/netlist_utils.py
liionpack/plots.py
liionpack/protocols.py
liionpack/sim_utils.py
liionpack/simulations.py
liionpack/solver_utils.py
liionpack/solvers.py
liionpack/utils.py
liionpack/version.pyi
liionpack/circuits/4p1s.asc
liionpack/circuits/4p1s.cir
liionpack/circuits/4p1s.txt
liionpack-0.4.0.dist-info/METADATA
liionpack-0.4.0.dist-info/WHEEL
liionpack-0.4.0.dist-info/licenses/LICENSE
liionpack-0.4.0.dist-info/RECORD
