Metadata-Version: 2.4
Name: liionpack
Version: 0.4.0
Summary: A battery pack simulator for PyBaMM
Project-URL: Bug Tracker, https://github.com/pybamm-team/liionpack/issues
Project-URL: Changelog, https://github.com/pybamm-team/liionpack/blob/develop/CHANGELOG.md
Project-URL: Documentation, https://liionpack.readthedocs.io/en/latest/
Project-URL: Homepage, https://github.com/pybamm-team/liionpack
Author-email: Tom Tranter <t.g.tranter@gmail.com>
License-Expression: MIT
License-File: LICENSE
Classifier: Development Status :: 4 - Beta
Classifier: Intended Audience :: Developers
Classifier: Intended Audience :: Science/Research
Classifier: License :: OSI Approved :: MIT License
Classifier: Programming Language :: Python
Classifier: Programming Language :: Python :: 3
Classifier: Programming Language :: Python :: 3 :: Only
Classifier: Programming Language :: Python :: 3.10
Classifier: Programming Language :: Python :: 3.11
Classifier: Programming Language :: Python :: 3.12
Classifier: Topic :: Scientific/Engineering
Requires-Python: <3.13,>=3.10
Requires-Dist: ipython
Requires-Dist: ipywidgets
Requires-Dist: lcapy
Requires-Dist: matplotlib
Requires-Dist: networkx
Requires-Dist: numpy
Requires-Dist: openpyxl
Requires-Dist: pandas
Requires-Dist: plotly
Requires-Dist: pybamm>=24.9
Requires-Dist: ray
Requires-Dist: redis
Requires-Dist: scikit-spatial
Requires-Dist: scipy
Requires-Dist: textwrapper
Requires-Dist: tqdm
Provides-Extra: dev
Requires-Dist: nbmake; extra == 'dev'
Requires-Dist: pytest; extra == 'dev'
